alerts/__init__.py
alerts/admin.py
alerts/alert.py
alerts/app.py
alerts/base.py
alerts/fields.py
alerts/forms.py
alerts/mixins.py
alerts/models.py
alerts/template_tools.py
alerts/tests.py
alerts/urls.py
alerts/views.py
alerts/fixtures/test-messages.json
alerts/management/__init__.py
alerts/management/commands/__init__.py
alerts/management/commands/batch_alerts.py
alerts/migrations/0001_initial.py
alerts/migrations/0002_auto_20150716_0346.py
alerts/migrations/0003_auto_20150827_0424.py
alerts/migrations/0004_auto_20161024_2027.py
alerts/migrations/0005_auto_20161108_1700.py
alerts/migrations/0006_auto_20170107_2355.py
alerts/migrations/0007_useralertsetting_filter_value.py
alerts/migrations/0008_auto_20180324_1624.py
alerts/migrations/0009_auto_20181220_1622.py
alerts/migrations/0010_message_root.py
alerts/migrations/0011_auto_20210820_1919.py
alerts/migrations/__init__.py
alerts/static/alerts/css/alerts.css
alerts/static/alerts/css/bootstrap.min.css
alerts/static/alerts/css/modal.css
alerts/static/alerts/css/sumoselect.css
alerts/static/alerts/js/alert.js
alerts/static/alerts/js/bootstrap.min.js
alerts/static/alerts/js/sumoselect.min.js
alerts/templates/alerts/alertsubscription_confirm_delete.html
alerts/templates/alerts/alertsubscription_form.html
alerts/templates/alerts/base.html
alerts/templates/alerts/email_default.txt
alerts/templates/alerts/fields.html
alerts/templates/alerts/menu.html
alerts/templates/alerts/message_form.html
alerts/templates/alerts/message_list.html
alerts/templates/alerts/new_base.html
alerts/templates/alerts/thread_list.html
alerts/templates/alerts/type_default.html
alerts/templates/alerts/useralert_list.html
alerts/templates/alerts/useralertsetting_form.html
alerts/templates/alerts/useralertsetting_list.html
alerts/templates/alerts/alert/batch_email.txt
alerts/templates/alerts/alert/email_footer.txt
alerts/templates/alerts/alert/email_message_alert.txt
alerts/templates/alerts/alert/message_alert.html
alerts/templatetags/__init__.py
django_boxed_alerts-2.0.0.dist-info/LICENSE
django_boxed_alerts-2.0.0.dist-info/METADATA
django_boxed_alerts-2.0.0.dist-info/WHEEL
django_boxed_alerts-2.0.0.dist-info/top_level.txt
django_boxed_alerts-2.0.0.dist-info/RECORD
