Metadata-Version: 2.2
Name: django-boxed-alerts
Version: 2.0.0
Summary: Robust user emailing and notification system for django web framework.
Home-page: https://gitlab.com/doctormo/django-boxed-alerts
Author: Martin Owens
Author-email: doctormo@gmail.com
License: AGPLv3
Platform: linux
Classifier: Intended Audience :: Developers
Classifier: Intended Audience :: Information Technology
Classifier: Intended Audience :: System Administrators
Classifier: Programming Language :: Python
Classifier: Programming Language :: Python :: 3.7
License-File: LICENSE
Requires-Dist: django>=4.0
Dynamic: author
Dynamic: author-email
Dynamic: classifier
Dynamic: description
Dynamic: home-page
Dynamic: license
Dynamic: platform
Dynamic: requires-dist
Dynamic: summary
